datalab_org_galvani-0.5.2.dist-info/licenses/LICENSES/GPL-3.0-or-later.txt
galvani/BioLogic.py
galvani/__init__.py
galvani/res2sqlite.py
datalab_org_galvani-0.5.2.dist-info/METADATA
datalab_org_galvani-0.5.2.dist-info/WHEEL
datalab_org_galvani-0.5.2.dist-info/entry_points.txt
datalab_org_galvani-0.5.2.dist-info/top_level.txt
datalab_org_galvani-0.5.2.dist-info/RECORD
