Metadata-Version: 2.4
Name: datalab-org-galvani
Version: 0.5.2
Summary: Open and process battery charger log data files: fork of original package `galvani`
Author-email: Chris Kerr <chris.kerr@mykolab.ch>
License: GPLv3+
Project-URL: Homepage, https://github.com/datalab-org/galvani-mirror
Project-URL: Issues, https://github.com/datalab-org/galvani-mirror
Classifier: Development Status :: 4 - Beta
Classifier: Intended Audience :: Developers
Classifier: Intended Audience :: Science/Research
Classifier: License :: OSI Approved :: GNU General Public License v3 or later (GPLv3+)
Classifier: Natural Language :: English
Classifier: Programming Language :: Python :: 3 :: Only
Classifier: Topic :: Scientific/Engineering :: Chemistry
Requires-Python: >=3.6
License-File: LICENSES/GPL-3.0-or-later.txt
Requires-Dist: numpy
Dynamic: license-file
